LICENSE
MANIFEST.in
README.md
setup.py
src/mongolock.py
src/mongolock.egg-info/PKG-INFO
src/mongolock.egg-info/SOURCES.txt
src/mongolock.egg-info/dependency_links.txt
src/mongolock.egg-info/not-zip-safe
src/mongolock.egg-info/requires.txt
src/mongolock.egg-info/top_level.txt