Metadata-Version: 1.1
Name: mongolock
Version: 1.0.1
Summary: Python Mongodb based Distributed Lock
Home-page: https://github.com/lorehov/mongolock
Author: Lev Orekhov
Author-email: lev.orekhov@gmail.com
License: BSD
Keywords: lock mongodb
Platform: UNKNOWN
Classifier: Intended Audience :: Developers
Classifier: Programming Language :: Python
Classifier: Programming Language :: Python :: 2
Classifier: Operating System :: OS Independent
Classifier: Topic :: Software Development :: Libraries
Classifier: Topic :: Software Development :: Libraries :: Python Modules
